skypro/__init__.py
skypro/commands/__init__.py
skypro/commands/pull_elexon_imbalance/README.md
skypro/commands/pull_elexon_imbalance/__init__.py
skypro/commands/pull_elexon_imbalance/main.py
skypro/commands/pull_elexon_imbalance/utils.py
skypro/commands/report/README.md
skypro/commands/report/__init__.py
skypro/commands/report/config/__init__.py
skypro/commands/report/config/config.py
skypro/commands/report/main.py
skypro/commands/report/microgrid_flow_calcs.py
skypro/commands/report/plots.py
skypro/commands/report/rates.py
skypro/commands/report/readings.py
skypro/commands/report/warnings.py
skypro/commands/simulator/README.md
skypro/commands/simulator/__init__.py
skypro/commands/simulator/algorithms/__init__.py
skypro/commands/simulator/algorithms/base.py
skypro/commands/simulator/algorithms/lp/__init__.py
skypro/commands/simulator/algorithms/lp/optimiser.py
skypro/commands/simulator/algorithms/price_curve/__init__.py
skypro/commands/simulator/algorithms/price_curve/algo.py
skypro/commands/simulator/algorithms/price_curve/microgrid.py
skypro/commands/simulator/algorithms/price_curve/peak.py
skypro/commands/simulator/algorithms/price_curve/system_state.py
skypro/commands/simulator/algorithms/rate_management.py
skypro/commands/simulator/algorithms/registry.py
skypro/commands/simulator/algorithms/utils.py
skypro/commands/simulator/cartesian.py
skypro/commands/simulator/config/__init__.py
skypro/commands/simulator/config/config.py
skypro/commands/simulator/config/curve.py
skypro/commands/simulator/config/parse_config.py
skypro/commands/simulator/main.py
skypro/commands/simulator/microgrid.py
skypro/commands/simulator/normalise_data.py
skypro/commands/simulator/profiler.py
skypro/commands/simulator/results.py
skypro/common/__init__.py
skypro/common/cli_utils/__init__.py
skypro/common/cli_utils/cli_utils.py
skypro/common/config/__init__.py
skypro/common/config/bill_match.py
skypro/common/config/data_source.py
skypro/common/config/data_source_csv.py
skypro-2.0.3.dist-info/METADATA
skypro-2.0.3.dist-info/WHEEL
skypro-2.0.3.dist-info/entry_points.txt
skypro-2.0.3.dist-info/licenses/LICENSE
skypro-2.0.3.dist-info/RECORD
