Metadata-Version: 2.4
Name: skypro
Version: 2.0.3
Summary: Skyprospector by Cepro
License: MIT
License-File: LICENSE
Author: damonrand
Author-email: damon@cepro.energy
Requires-Python: >=3.10,<4.0
Classifier: License :: OSI Approved :: MIT License
Classifier: Programming Language :: Python :: 3
Classifier: Programming Language :: Python :: 3.10
Classifier: Programming Language :: Python :: 3.11
Classifier: Programming Language :: Python :: 3.12
Classifier: Programming Language :: Python :: 3.13
Classifier: Programming Language :: Python :: 3.14
Requires-Dist: arrow (>=1.3.0,<2.0.0)
Requires-Dist: marshmallow (>=3.21.3,<4.0.0)
Requires-Dist: marshmallow-dataclass (>=8.7.0,<9.0.0)
Requires-Dist: pandas (>=2.2.2,<3.0.0)
Requires-Dist: pendulum (>=3.0.0,<4.0.0)
Requires-Dist: plotly (>=5.21.0,<6.0.0)
Requires-Dist: psycopg2-binary (>=2.9.10,<3.0.0)
Requires-Dist: pulp (>=2.9.0,<3.0.0)
Requires-Dist: pyyaml (>=6.0.1,<7.0.0)
Requires-Dist: requests (>=2.32.3,<3.0.0)
Requires-Dist: ruff (>=0.11.2,<0.12.0)
Requires-Dist: sqlalchemy (>=2.0.37,<3.0.0)
Requires-Dist: streamlit (>=1.45.1,<2.0.0)
Requires-Dist: tabulate (>=0.9.0,<0.10.0)
